pyonesend/__init__.py
pyonesend/cli.py
pyonesend/security.py
pyonesend/server.py
pyonesend/utils.py
pyonesend-1.0.1.dist-info/licenses/LICENSE
pyonesend-1.0.1.dist-info/METADATA
pyonesend-1.0.1.dist-info/WHEEL
pyonesend-1.0.1.dist-info/entry_points.txt
pyonesend-1.0.1.dist-info/top_level.txt
pyonesend-1.0.1.dist-info/RECORD
